<?xml version="1.0"?>
<ArrayOfRoute xmlns:xsi="http://www.w3.org/2001/XMLSchema-instance" xmlns:xsd="http://www.w3.org/2001/XMLSchema">
  <Route>
    <Name>АК3</Name>
    <NamePen>
      <StringItem>
        <Value>pBlack</Value>
      </StringItem>
      <StringItem>
        <Value>pBlue</Value>
      </StringItem>
    </NamePen>
    <NameGraphics>
      <StringItem>
        <Value>kl96_24</Value>
      </StringItem>
      <StringItem>
        <Value>l0_0</Value>
      </StringItem>
      <StringItem>
        <Value>l2_1</Value>
      </StringItem>
      <StringItem>
        <Value>l4_0</Value>
      </StringItem>
      <StringItem>
        <Value>l7_2</Value>
      </StringItem>
      <StringItem>
        <Value>l10_3</Value>
      </StringItem>
      <StringItem>
        <Value>kl161_118</Value>
      </StringItem>
      <StringItem>
        <Value>kl116_51</Value>
      </StringItem>
      <StringItem>
        <Value>l31_30</Value>
      </StringItem>
      <StringItem>
        <Value>l37_14</Value>
      </StringItem>
      <StringItem>
        <Value>l38_37</Value>
      </StringItem>
      <StringItem>
        <Value>kl162_8</Value>
      </StringItem>
      <StringItem>
        <Value>vl266_204</Value>
      </StringItem>
    </NameGraphics>
    <ValueName>__STD_1</ValueName>
    <TypRoute>0</TypRoute>
    <ValueType>BitStruct</ValueType>
    <ValuePos>0</ValuePos>
  </Route>
  <Route>
    <Name>GK3</Name>
    <NamePen>
      <StringItem>
        <Value>pBlack</Value>
      </StringItem>
      <StringItem>
        <Value>pBlue</Value>
      </StringItem>
    </NamePen>
    <NameGraphics>
      <StringItem>
        <Value>vl268_234</Value>
      </StringItem>
      <StringItem>
        <Value>kl97_27</Value>
      </StringItem>
      <StringItem>
        <Value>l1_0</Value>
      </StringItem>
      <StringItem>
        <Value>l2_1</Value>
      </StringItem>
      <StringItem>
        <Value>l4_0</Value>
      </StringItem>
      <StringItem>
        <Value>l7_2</Value>
      </StringItem>
      <StringItem>
        <Value>l10_3</Value>
      </StringItem>
      <StringItem>
        <Value>kl161_118</Value>
      </StringItem>
      <StringItem>
        <Value>vl269_97</Value>
      </StringItem>
      <StringItem>
        <Value>kl117_76</Value>
      </StringItem>
      <StringItem>
        <Value>l32_20</Value>
      </StringItem>
      <StringItem>
        <Value>l37_14</Value>
      </StringItem>
      <StringItem>
        <Value>l38_37</Value>
      </StringItem>
      <StringItem>
        <Value>kl162_8</Value>
      </StringItem>
    </NameGraphics>
    <ValueName>__STD_1</ValueName>
    <TypRoute>0</TypRoute>
    <ValueType>BitStruct</ValueType>
    <ValuePos>1</ValuePos>
  </Route>
  <Route>
    <Name>SU1</Name>
    <NamePen>
      <StringItem>
        <Value>pBlack</Value>
      </StringItem>
      <StringItem>
        <Value>pBlue</Value>
      </StringItem>
    </NamePen>
    <NameGraphics>
      <StringItem>
        <Value>vl270_77</Value>
      </StringItem>
      <StringItem>
        <Value>kl98_27</Value>
      </StringItem>
      <StringItem>
        <Value>l3_2</Value>
      </StringItem>
      <StringItem>
        <Value>l4_0</Value>
      </StringItem>
      <StringItem>
        <Value>l7_2</Value>
      </StringItem>
      <StringItem>
        <Value>l10_3</Value>
      </StringItem>
      <StringItem>
        <Value>kl161_118</Value>
      </StringItem>
      <StringItem>
        <Value>vl271_121</Value>
      </StringItem>
      <StringItem>
        <Value>kl128_45</Value>
      </StringItem>
      <StringItem>
        <Value>l79_46</Value>
      </StringItem>
      <StringItem>
        <Value>l81_72</Value>
      </StringItem>
      <StringItem>
        <Value>kl176_174</Value>
      </StringItem>
    </NameGraphics>
    <ValueName>__STD_1</ValueName>
    <TypRoute>0</TypRoute>
    <ValueType>BitStruct</ValueType>
    <ValuePos>2</ValuePos>
  </Route>
  <Route>
    <Name>В13</Name>
    <NamePen>
      <StringItem>
        <Value>pBlack</Value>
      </StringItem>
      <StringItem>
        <Value>pBlue</Value>
      </StringItem>
    </NamePen>
    <NameGraphics>
      <StringItem>
        <Value>vl272_251</Value>
      </StringItem>
      <StringItem>
        <Value>kl99_57</Value>
      </StringItem>
      <StringItem>
        <Value>l5_3</Value>
      </StringItem>
      <StringItem>
        <Value>l7_2</Value>
      </StringItem>
      <StringItem>
        <Value>l10_3</Value>
      </StringItem>
      <StringItem>
        <Value>kl161_118</Value>
      </StringItem>
    </NameGraphics>
    <ValueName>__STD_1</ValueName>
    <TypRoute>0</TypRoute>
    <ValueType>BitStruct</ValueType>
    <ValuePos>5</ValuePos>
  </Route>
  <Route>
    <Name>КР</Name>
    <NamePen>
      <StringItem>
        <Value>pBlack</Value>
      </StringItem>
      <StringItem>
        <Value>pBlue</Value>
      </StringItem>
    </NamePen>
    <NameGraphics>
      <StringItem>
        <Value>vl273_177</Value>
      </StringItem>
      <StringItem>
        <Value>kl100_86</Value>
      </StringItem>
      <StringItem>
        <Value>l6_1</Value>
      </StringItem>
      <StringItem>
        <Value>l9_0</Value>
      </StringItem>
      <StringItem>
        <Value>l10_3</Value>
      </StringItem>
      <StringItem>
        <Value>kl161_118</Value>
      </StringItem>
      <StringItem>
        <Value>vl274_127</Value>
      </StringItem>
      <StringItem>
        <Value>kl103_1</Value>
      </StringItem>
      <StringItem>
        <Value>l85_18</Value>
      </StringItem>
      <StringItem>
        <Value>l86_40</Value>
      </StringItem>
      <StringItem>
        <Value>l88_33</Value>
      </StringItem>
      <StringItem>
        <Value>kl163_63</Value>
      </StringItem>
    </NameGraphics>
    <ValueName>__STD_1</ValueName>
    <TypRoute>0</TypRoute>
    <ValueType>BitStruct</ValueType>
    <ValuePos>3</ValuePos>
  </Route>
  <Route>
    <Name>U17</Name>
    <NamePen>
      <StringItem>
        <Value>pBlack</Value>
      </StringItem>
      <StringItem>
        <Value>pBlue</Value>
      </StringItem>
    </NamePen>
    <NameGraphics>
      <StringItem>
        <Value>vl276_112</Value>
      </StringItem>
      <StringItem>
        <Value>kl101_12</Value>
      </StringItem>
      <StringItem>
        <Value>l8_2</Value>
      </StringItem>
      <StringItem>
        <Value>l9_0</Value>
      </StringItem>
      <StringItem>
        <Value>l10_3</Value>
      </StringItem>
      <StringItem>
        <Value>kl161_118</Value>
      </StringItem>
      <StringItem>
        <Value>vl336_157</Value>
      </StringItem>
      <StringItem>
        <Value>kl104_76</Value>
      </StringItem>
      <StringItem>
        <Value>l87_16</Value>
      </StringItem>
      <StringItem>
        <Value>l88_33</Value>
      </StringItem>
      <StringItem>
        <Value>kl163_63</Value>
      </StringItem>
    </NameGraphics>
    <ValueName>__STD_1</ValueName>
    <TypRoute>0</TypRoute>
    <ValueType>BitStruct</ValueType>
    <ValuePos>4</ValuePos>
  </Route>
  <Route>
    <Name>kKR</Name>
    <NamePen>
      <StringItem>
        <Value>pBlack</Value>
      </StringItem>
      <StringItem>
        <Value>pBlue</Value>
      </StringItem>
    </NamePen>
    <NameGraphics>
      <StringItem>
        <Value>vl277_271</Value>
      </StringItem>
      <StringItem>
        <Value>kl109_106</Value>
      </StringItem>
      <StringItem>
        <Value>l13_3</Value>
      </StringItem>
      <StringItem>
        <Value>l15_5</Value>
      </StringItem>
      <StringItem>
        <Value>kl179_124</Value>
      </StringItem>
      <StringItem>
        <Value>vl275_200</Value>
      </StringItem>
      <StringItem>
        <Value>kl106_42</Value>
      </StringItem>
      <StringItem>
        <Value>l93_57</Value>
      </StringItem>
      <StringItem>
        <Value>l95_75</Value>
      </StringItem>
      <StringItem>
        <Value>kl180_43</Value>
      </StringItem>
      <StringItem>
        <Value>l90_72</Value>
      </StringItem>
      <StringItem>
        <Value>vl275_200</Value>
      </StringItem>
      <StringItem>
        <Value>kl106_42</Value>
      </StringItem>
      <StringItem>
        <Value>l90_72</Value>
      </StringItem>
      <StringItem>
        <Value>l93_57</Value>
      </StringItem>
      <StringItem>
        <Value>l95_75</Value>
      </StringItem>
      <StringItem>
        <Value>kl180_43</Value>
      </StringItem>
    </NameGraphics>
    <ValueName>__MNEMO_RES_52</ValueName>
    <TypRoute>0</TypRoute>
    <ValueType>BitStruct</ValueType>
    <ValuePos>30</ValuePos>
  </Route>
  <Route>
    <Name>kPK8</Name>
    <NamePen>
      <StringItem>
        <Value>pBlack</Value>
      </StringItem>
      <StringItem>
        <Value>pBlue</Value>
      </StringItem>
    </NamePen>
    <NameGraphics>
      <StringItem>
        <Value>vl278_84</Value>
      </StringItem>
      <StringItem>
        <Value>kl111_86</Value>
      </StringItem>
      <StringItem>
        <Value>kl110_47</Value>
      </StringItem>
      <StringItem>
        <Value>l14_0</Value>
      </StringItem>
      <StringItem>
        <Value>l15_5</Value>
      </StringItem>
      <StringItem>
        <Value>kl179_124</Value>
      </StringItem>
      <StringItem>
        <Value>vl279_129</Value>
      </StringItem>
      <StringItem>
        <Value>kl108_85</Value>
      </StringItem>
      <StringItem>
        <Value>kl107_35</Value>
      </StringItem>
      <StringItem>
        <Value>l94_36</Value>
      </StringItem>
      <StringItem>
        <Value>l95_75</Value>
      </StringItem>
      <StringItem>
        <Value>kl180_43</Value>
      </StringItem>
      <StringItem>
        <Value>vl279_129</Value>
      </StringItem>
      <StringItem>
        <Value>kl108_85</Value>
      </StringItem>
      <StringItem>
        <Value>kl107_35</Value>
      </StringItem>
      <StringItem>
        <Value>l94_36</Value>
      </StringItem>
      <StringItem>
        <Value>l95_75</Value>
      </StringItem>
      <StringItem>
        <Value>kl180_43</Value>
      </StringItem>
    </NameGraphics>
    <ValueName>__STD_1</ValueName>
    <TypRoute>0</TypRoute>
    <ValueType>BitStruct</ValueType>
    <ValuePos>6</ValuePos>
  </Route>
  <Route>
    <Name>klap1</Name>
    <NamePen>
      <StringItem>
        <Value>pBlack</Value>
      </StringItem>
      <StringItem>
        <Value>pBlue</Value>
      </StringItem>
    </NamePen>
    <NameGraphics>
      <StringItem>
        <Value>kl180_43</Value>
      </StringItem>
      <StringItem>
        <Value>l12_11</Value>
      </StringItem>
      <StringItem>
        <Value>l12_1</Value>
      </StringItem>
      <StringItem>
        <Value>kl185_6</Value>
      </StringItem>
      <StringItem>
        <Value>kl187_175</Value>
      </StringItem>
      <StringItem>
        <Value>kl186_185</Value>
      </StringItem>
      <StringItem>
        <Value>kl251_172</Value>
      </StringItem>
    </NameGraphics>
    <ValueName>__STD_1</ValueName>
    <TypRoute>0</TypRoute>
    <ValueType>BitStruct</ValueType>
    <ValuePos>7</ValuePos>
  </Route>
  <Route>
    <Name>std1i6</Name>
    <NamePen>
      <StringItem>
        <Value>pBlack</Value>
      </StringItem>
      <StringItem>
        <Value>pBlue</Value>
      </StringItem>
    </NamePen>
    <NameGraphics>
      <StringItem>
        <Value>l244_176</Value>
      </StringItem>
      <StringItem>
        <Value>l239_155</Value>
      </StringItem>
      <StringItem>
        <Value>kl237_37</Value>
      </StringItem>
      <StringItem>
        <Value>l233_31</Value>
      </StringItem>
      <StringItem>
        <Value>kl240_165</Value>
      </StringItem>
      <StringItem>
        <Value>kl235_92</Value>
      </StringItem>
      <StringItem>
        <Value>l225_202</Value>
      </StringItem>
      <StringItem>
        <Value>kl226_190</Value>
      </StringItem>
      <StringItem>
        <Value>kl243_119</Value>
      </StringItem>
      <StringItem>
        <Value>kl242_102</Value>
      </StringItem>
      <StringItem>
        <Value>kl227_140</Value>
      </StringItem>
    </NameGraphics>
    <ValueName>__STD_1</ValueName>
    <TypRoute>0</TypRoute>
    <ValueType>BitStruct</ValueType>
    <ValuePos>8</ValuePos>
  </Route>
  <Route>
    <Name>std2is6</Name>
    <NamePen>
      <StringItem>
        <Value>pBlack</Value>
      </StringItem>
      <StringItem>
        <Value>pBlue</Value>
      </StringItem>
    </NamePen>
    <NameGraphics>
      <StringItem>
        <Value>kl243_119</Value>
      </StringItem>
      <StringItem>
        <Value>l244_176</Value>
      </StringItem>
      <StringItem>
        <Value>kl242_102</Value>
      </StringItem>
      <StringItem>
        <Value>l239_155</Value>
      </StringItem>
      <StringItem>
        <Value>kl241_0</Value>
      </StringItem>
      <StringItem>
        <Value>kl238_82</Value>
      </StringItem>
      <StringItem>
        <Value>l234_13</Value>
      </StringItem>
      <StringItem>
        <Value>kl236_188</Value>
      </StringItem>
      <StringItem>
        <Value>l231_20</Value>
      </StringItem>
      <StringItem>
        <Value>kl232_81</Value>
      </StringItem>
      <StringItem>
        <Value>kl229_38</Value>
      </StringItem>
    </NameGraphics>
    <ValueName>__STD_1</ValueName>
    <TypRoute>0</TypRoute>
    <ValueType>BitStruct</ValueType>
    <ValuePos>9</ValuePos>
  </Route>
  <Route>
    <Name>srabTD</Name>
    <NamePen>
      <StringItem>
        <Value>pBlack</Value>
      </StringItem>
      <StringItem>
        <Value>pBlue</Value>
      </StringItem>
    </NamePen>
    <NameGraphics>
      <StringItem>
        <Value>l16_11</Value>
      </StringItem>
      <StringItem>
        <Value>l17_13</Value>
      </StringItem>
      <StringItem>
        <Value>l24_3</Value>
      </StringItem>
      <StringItem>
        <Value>l25_1</Value>
      </StringItem>
      <StringItem>
        <Value>l26_11</Value>
      </StringItem>
      <StringItem>
        <Value>kl189_108</Value>
      </StringItem>
      <StringItem>
        <Value>kl255_172</Value>
      </StringItem>
    </NameGraphics>
    <ValueName>__STD_1</ValueName>
    <TypRoute>0</TypRoute>
    <ValueType>BitStruct</ValueType>
    <ValuePos>10</ValuePos>
  </Route>
  <Route>
    <Name>2naSR</Name>
    <NamePen>
      <StringItem>
        <Value>pBlack</Value>
      </StringItem>
      <StringItem>
        <Value>pBlue</Value>
      </StringItem>
    </NamePen>
    <NameGraphics>
      <StringItem>
        <Value>l16_11</Value>
      </StringItem>
      <StringItem>
        <Value>l17_13</Value>
      </StringItem>
      <StringItem>
        <Value>l18_9</Value>
      </StringItem>
      <StringItem>
        <Value>l19_17</Value>
      </StringItem>
      <StringItem>
        <Value>l20_8</Value>
      </StringItem>
      <StringItem>
        <Value>l22_12</Value>
      </StringItem>
      <StringItem>
        <Value>kl169_60</Value>
      </StringItem>
      <StringItem>
        <Value>kl171_58</Value>
      </StringItem>
    </NameGraphics>
    <ValueName>__STD_1</ValueName>
    <TypRoute>0</TypRoute>
    <ValueType>BitStruct</ValueType>
    <ValuePos>11</ValuePos>
  </Route>
  <Route>
    <Name>1naSR</Name>
    <NamePen>
      <StringItem>
        <Value>pBlack</Value>
      </StringItem>
      <StringItem>
        <Value>pBlue</Value>
      </StringItem>
    </NamePen>
    <NameGraphics>
      <StringItem>
        <Value>l39_16</Value>
      </StringItem>
      <StringItem>
        <Value>l41_13</Value>
      </StringItem>
      <StringItem>
        <Value>kl170_2</Value>
      </StringItem>
    </NameGraphics>
    <ValueName>__STD_1</ValueName>
    <TypRoute>0</TypRoute>
    <ValueType>BitStruct</ValueType>
    <ValuePos>12</ValuePos>
  </Route>
  <Route>
    <Name>TD_Podkl</Name>
    <NamePen>
      <StringItem>
        <Value>pBlack</Value>
      </StringItem>
      <StringItem>
        <Value>pBlue</Value>
      </StringItem>
    </NamePen>
    <NameGraphics>
      <StringItem>
        <Value>kl188_10</Value>
      </StringItem>
      <StringItem>
        <Value>kl253_242</Value>
      </StringItem>
      <StringItem>
        <Value>l42_0</Value>
      </StringItem>
      <StringItem>
        <Value>kl165_161</Value>
      </StringItem>
    </NameGraphics>
    <ValueName>__STD_1</ValueName>
    <TypRoute>0</TypRoute>
    <ValueType>BitStruct</ValueType>
    <ValuePos>13</ValuePos>
  </Route>
  <Route>
    <Name>ОВК6</Name>
    <NamePen>
      <StringItem>
        <Value>pBlack</Value>
      </StringItem>
      <StringItem>
        <Value>pBlue</Value>
      </StringItem>
    </NamePen>
    <NameGraphics>
      <StringItem>
        <Value>vl281_268</Value>
      </StringItem>
      <StringItem>
        <Value>kl113_70</Value>
      </StringItem>
      <StringItem>
        <Value>kl112_50</Value>
      </StringItem>
      <StringItem>
        <Value>l43_37</Value>
      </StringItem>
      <StringItem>
        <Value>kl280_56</Value>
      </StringItem>
    </NameGraphics>
    <ValueName>__STD_1</ValueName>
    <TypRoute>0</TypRoute>
    <ValueType>BitStruct</ValueType>
    <ValuePos>14</ValuePos>
  </Route>
  <Route>
    <Name>sr1</Name>
    <NamePen>
      <StringItem>
        <Value>pBlack</Value>
      </StringItem>
      <StringItem>
        <Value>pBlue</Value>
      </StringItem>
    </NamePen>
    <NameGraphics>
      <StringItem>
        <Value>kl192_167</Value>
      </StringItem>
      <StringItem>
        <Value>l45_2</Value>
      </StringItem>
      <StringItem>
        <Value>l46_3</Value>
      </StringItem>
      <StringItem>
        <Value>l47_6</Value>
      </StringItem>
      <StringItem>
        <Value>kl181_148</Value>
      </StringItem>
      <StringItem>
        <Value>kl209_141</Value>
      </StringItem>
    </NameGraphics>
    <ValueName>__STD_1</ValueName>
    <TypRoute>0</TypRoute>
    <ValueType>BitStruct</ValueType>
    <ValuePos>15</ValuePos>
  </Route>
  <Route>
    <Name>ОВК5</Name>
    <NamePen>
      <StringItem>
        <Value>pBlack</Value>
      </StringItem>
      <StringItem>
        <Value>pBlue</Value>
      </StringItem>
    </NamePen>
    <NameGraphics>
      <StringItem>
        <Value>vl282_223</Value>
      </StringItem>
      <StringItem>
        <Value>kl119_2</Value>
      </StringItem>
      <StringItem>
        <Value>kl122_69</Value>
      </StringItem>
      <StringItem>
        <Value>l33_7</Value>
      </StringItem>
      <StringItem>
        <Value>l38_37</Value>
      </StringItem>
      <StringItem>
        <Value>kl162_8</Value>
      </StringItem>
    </NameGraphics>
    <ValueName>__STD_1</ValueName>
    <TypRoute>0</TypRoute>
    <ValueType>BitStruct</ValueType>
    <ValuePos>16</ValuePos>
  </Route>
  <Route>
    <Name>ch6_gk</Name>
    <NamePen>
      <StringItem>
        <Value>pBlack</Value>
      </StringItem>
      <StringItem>
        <Value>pBlue</Value>
      </StringItem>
    </NamePen>
    <NameGraphics>
      <StringItem>
        <Value>vl283_204</Value>
      </StringItem>
      <StringItem>
        <Value>kl120_91</Value>
      </StringItem>
      <StringItem>
        <Value>l34_5</Value>
      </StringItem>
      <StringItem>
        <Value>kl123_64</Value>
      </StringItem>
      <StringItem>
        <Value>kl118_101</Value>
      </StringItem>
      <StringItem>
        <Value>l36_0</Value>
      </StringItem>
      <StringItem>
        <Value>l38_37</Value>
      </StringItem>
      <StringItem>
        <Value>kl162_8</Value>
      </StringItem>
    </NameGraphics>
    <ValueName>__STD_1</ValueName>
    <TypRoute>0</TypRoute>
    <ValueType>BitStruct</ValueType>
    <ValuePos>17</ValuePos>
  </Route>
  <Route>
    <Name>ch54</Name>
    <NamePen>
      <StringItem>
        <Value>pBlack</Value>
      </StringItem>
      <StringItem>
        <Value>pBlue</Value>
      </StringItem>
    </NamePen>
    <NameGraphics>
      <StringItem>
        <Value>kl121_21</Value>
      </StringItem>
      <StringItem>
        <Value>l35_11</Value>
      </StringItem>
      <StringItem>
        <Value>kl127_71</Value>
      </StringItem>
      <StringItem>
        <Value>kl130_26</Value>
      </StringItem>
      <StringItem>
        <Value>kl125_122</Value>
      </StringItem>
      <StringItem>
        <Value>kl124_9</Value>
      </StringItem>
      <StringItem>
        <Value>l36_0</Value>
      </StringItem>
      <StringItem>
        <Value>l38_37</Value>
      </StringItem>
      <StringItem>
        <Value>kl162_8</Value>
      </StringItem>
      <StringItem>
        <Value>kl129_74</Value>
      </StringItem>
      <StringItem>
        <Value>l80_29</Value>
      </StringItem>
      <StringItem>
        <Value>l81_72</Value>
      </StringItem>
      <StringItem>
        <Value>kl176_174</Value>
      </StringItem>
      <StringItem>
        <Value>vl284_32</Value>
      </StringItem>
      <StringItem>
        <Value>vl285_193</Value>
      </StringItem>
    </NameGraphics>
    <ValueName>__STD_1</ValueName>
    <TypRoute>0</TypRoute>
    <ValueType>BitStruct</ValueType>
    <ValuePos>18</ValuePos>
  </Route>
  <Route>
    <Name>PK_L11</Name>
    <NamePen>
      <StringItem>
        <Value>pBlack</Value>
      </StringItem>
      <StringItem>
        <Value>pBlue</Value>
      </StringItem>
    </NamePen>
    <NameGraphics>
      <StringItem>
        <Value>vl309_281</Value>
      </StringItem>
      <StringItem>
        <Value>kl140_31</Value>
      </StringItem>
      <StringItem>
        <Value>l78_6</Value>
      </StringItem>
      <StringItem>
        <Value>kl142_44</Value>
      </StringItem>
      <StringItem>
        <Value>kl141_80</Value>
      </StringItem>
      <StringItem>
        <Value>kl221_49</Value>
      </StringItem>
    </NameGraphics>
    <ValueName>__STD_1</ValueName>
    <TypRoute>0</TypRoute>
    <ValueType>BitStruct</ValueType>
    <ValuePos>19</ValuePos>
  </Route>
  <Route>
    <Name>isOK52</Name>
    <NamePen>
      <StringItem>
        <Value>pBlack</Value>
      </StringItem>
      <StringItem>
        <Value>pBlue</Value>
      </StringItem>
    </NamePen>
    <NameGraphics>
      <StringItem>
        <Value>l48_21</Value>
      </StringItem>
      <StringItem>
        <Value>l174_137</Value>
      </StringItem>
      <StringItem>
        <Value>l175_20</Value>
      </StringItem>
      <StringItem>
        <Value>l50_30</Value>
      </StringItem>
      <StringItem>
        <Value>kl173_121</Value>
      </StringItem>
      <StringItem>
        <Value>kl210_166</Value>
      </StringItem>
      <StringItem>
        <Value>kl217_152</Value>
      </StringItem>
    </NameGraphics>
    <ValueName>__STD_1</ValueName>
    <TypRoute>0</TypRoute>
    <ValueType>BitStruct</ValueType>
    <ValuePos>20</ValuePos>
  </Route>
  <Route>
    <Name>ok52_ok53</Name>
    <NamePen>
      <StringItem>
        <Value>pBlack</Value>
      </StringItem>
      <StringItem>
        <Value>pBlue</Value>
      </StringItem>
    </NamePen>
    <NameGraphics>
      <StringItem>
        <Value>l73_28</Value>
      </StringItem>
      <StringItem>
        <Value>kl184_26</Value>
      </StringItem>
      <StringItem>
        <Value>kl183_56</Value>
      </StringItem>
      <StringItem>
        <Value>kl182_140</Value>
      </StringItem>
    </NameGraphics>
    <ValueName>__STD_1</ValueName>
    <TypRoute>0</TypRoute>
    <ValueType>BitStruct</ValueType>
    <ValuePos>21</ValuePos>
  </Route>
  <Route>
    <Name>ok52</Name>
    <NamePen>
      <StringItem>
        <Value>pen1</Value>
      </StringItem>
      <StringItem>
        <Value>pen1</Value>
      </StringItem>
    </NamePen>
    <NameGraphics>
      <StringItem>
        <Value>kl211_168</Value>
      </StringItem>
    </NameGraphics>
    <ValueName>__STD_1</ValueName>
    <TypRoute>0</TypRoute>
    <ValueType>BitStruct</ValueType>
    <ValuePos>22</ValuePos>
  </Route>
  <Route>
    <Name>isOK53</Name>
    <NamePen>
      <StringItem>
        <Value>pBlack</Value>
      </StringItem>
      <StringItem>
        <Value>pBlue</Value>
      </StringItem>
    </NamePen>
    <NameGraphics>
      <StringItem>
        <Value>kl214_131</Value>
      </StringItem>
      <StringItem>
        <Value>l74_14</Value>
      </StringItem>
      <StringItem>
        <Value>kl190_133</Value>
      </StringItem>
      <StringItem>
        <Value>l76_59</Value>
      </StringItem>
      <StringItem>
        <Value>l75_4</Value>
      </StringItem>
    </NameGraphics>
    <ValueName>__STD_1</ValueName>
    <TypRoute>0</TypRoute>
    <ValueType>BitStruct</ValueType>
    <ValuePos>23</ValuePos>
  </Route>
  <Route>
    <Name>naBS_SUS</Name>
    <NamePen>
      <StringItem>
        <Value>pBlack</Value>
      </StringItem>
      <StringItem>
        <Value>pBlue</Value>
      </StringItem>
    </NamePen>
    <NameGraphics>
      <StringItem>
        <Value>kl193_117</Value>
      </StringItem>
      <StringItem>
        <Value>l51_45</Value>
      </StringItem>
      <StringItem>
        <Value>kl219_80</Value>
      </StringItem>
      <StringItem>
        <Value>kl131_63</Value>
      </StringItem>
      <StringItem>
        <Value>kl126_83</Value>
      </StringItem>
      <StringItem>
        <Value>kl218_36</Value>
      </StringItem>
      <StringItem>
        <Value>l69_55</Value>
      </StringItem>
      <StringItem>
        <Value>kl191_35</Value>
      </StringItem>
      <StringItem>
        <Value>l54_12</Value>
      </StringItem>
      <StringItem>
        <Value>l52_28</Value>
      </StringItem>
      <StringItem>
        <Value>l56_4</Value>
      </StringItem>
      <StringItem>
        <Value>l64_19</Value>
      </StringItem>
      <StringItem>
        <Value>kl164_77</Value>
      </StringItem>
    </NameGraphics>
    <ValueName>__STD_1</ValueName>
    <TypRoute>0</TypRoute>
    <ValueType>BitStruct</ValueType>
    <ValuePos>24</ValuePos>
  </Route>
  <Route>
    <Name>naBS</Name>
    <NamePen>
      <StringItem>
        <Value>pBlack</Value>
      </StringItem>
      <StringItem>
        <Value>pBlue</Value>
      </StringItem>
    </NamePen>
    <NameGraphics>
      <StringItem>
        <Value>kl194_146</Value>
      </StringItem>
      <StringItem>
        <Value>l63_58</Value>
      </StringItem>
      <StringItem>
        <Value>kl144_2</Value>
      </StringItem>
      <StringItem>
        <Value>kl143_19</Value>
      </StringItem>
      <StringItem>
        <Value>kl178_46</Value>
      </StringItem>
      <StringItem>
        <Value>kl202_198</Value>
      </StringItem>
      <StringItem>
        <Value>kl201_23</Value>
      </StringItem>
      <StringItem>
        <Value>l348_112</Value>
      </StringItem>
    </NameGraphics>
    <ValueName>__STD_1</ValueName>
    <TypRoute>0</TypRoute>
    <ValueType>BitStruct</ValueType>
    <ValuePos>25</ValuePos>
  </Route>
  <Route>
    <Name>akselerometr</Name>
    <NamePen>
      <StringItem>
        <Value>pen1</Value>
      </StringItem>
      <StringItem>
        <Value>pen1</Value>
      </StringItem>
    </NamePen>
    <NameGraphics>
      <StringItem>
        <Value>kl313_0</Value>
      </StringItem>
      <StringItem>
        <Value>vl372_168</Value>
      </StringItem>
    </NameGraphics>
    <ValueName>__STD_1</ValueName>
    <TypRoute>0</TypRoute>
    <ValueType>BitStruct</ValueType>
    <ValuePos>26</ValuePos>
  </Route>
  <Route>
    <Name>Key_STD1</Name>
    <NamePen>
      <StringItem>
        <Value>pen1</Value>
      </StringItem>
      <StringItem>
        <Value>pen1</Value>
      </StringItem>
      <StringItem>
        <Value>pen1</Value>
      </StringItem>
    </NamePen>
    <NameGraphics>
      <StringItem>
        <Value>kl208_149</Value>
      </StringItem>
    </NameGraphics>
    <ValueName>__STD_2</ValueName>
    <TypRoute>0</TypRoute>
    <ValueType>BitStruct</ValueType>
    <ValuePos>0</ValuePos>
  </Route>
  <Route>
    <Name>Key_STD2</Name>
    <NamePen>
      <StringItem>
        <Value>pen1</Value>
      </StringItem>
      <StringItem>
        <Value>pen1</Value>
      </StringItem>
      <StringItem>
        <Value>pen1</Value>
      </StringItem>
    </NamePen>
    <NameGraphics>
      <StringItem>
        <Value>kl207_101</Value>
      </StringItem>
    </NameGraphics>
    <ValueName>__STD_2</ValueName>
    <TypRoute>0</TypRoute>
    <ValueType>BitStruct</ValueType>
    <ValuePos>1</ValuePos>
  </Route>
  <Route>
    <Name>key_SR1</Name>
    <NamePen>
      <StringItem>
        <Value>pen1</Value>
      </StringItem>
      <StringItem>
        <Value>pen1</Value>
      </StringItem>
      <StringItem>
        <Value>pen1</Value>
      </StringItem>
    </NamePen>
    <NameGraphics>
      <StringItem>
        <Value>kl209_141</Value>
      </StringItem>
    </NameGraphics>
    <ValueName>__STD_2</ValueName>
    <TypRoute>0</TypRoute>
    <ValueType>BitStruct</ValueType>
    <ValuePos>2</ValuePos>
  </Route>
  <Route>
    <Name>Key_1</Name>
    <NamePen>
      <StringItem>
        <Value>pen1</Value>
      </StringItem>
      <StringItem>
        <Value>pen1</Value>
      </StringItem>
      <StringItem>
        <Value>pen1</Value>
      </StringItem>
    </NamePen>
    <NameGraphics>
      <StringItem>
        <Value>kl154_147</Value>
      </StringItem>
      <StringItem>
        <Value>kl155_50</Value>
      </StringItem>
    </NameGraphics>
    <ValueName>__STD_2</ValueName>
    <TypRoute>0</TypRoute>
    <ValueType>BitStruct</ValueType>
    <ValuePos>3</ValuePos>
  </Route>
  <Route>
    <Name>Key_2</Name>
    <NamePen>
      <StringItem>
        <Value>pBlack</Value>
      </StringItem>
      <StringItem>
        <Value>pBlue</Value>
      </StringItem>
      <StringItem>
        <Value>pBlue</Value>
      </StringItem>
    </NamePen>
    <NameGraphics>
      <StringItem>
        <Value>kl158_3</Value>
      </StringItem>
      <StringItem>
        <Value>kl157_107</Value>
      </StringItem>
      <StringItem>
        <Value>kl156_150</Value>
      </StringItem>
    </NameGraphics>
    <ValueName>__STD_2</ValueName>
    <TypRoute>0</TypRoute>
    <ValueType>BitStruct</ValueType>
    <ValuePos>4</ValuePos>
  </Route>
  <Route>
    <Name>Key_SR_DP</Name>
    <NamePen>
      <StringItem>
        <Value>pen1</Value>
      </StringItem>
      <StringItem>
        <Value>pen1</Value>
      </StringItem>
      <StringItem>
        <Value>pen1</Value>
      </StringItem>
    </NamePen>
    <NameGraphics>
      <StringItem>
        <Value>kl206_137</Value>
      </StringItem>
    </NameGraphics>
    <ValueName>__STD_2</ValueName>
    <TypRoute>0</TypRoute>
    <ValueType>BitStruct</ValueType>
    <ValuePos>5</ValuePos>
  </Route>
  <Route>
    <Name>Key_sSR</Name>
    <NamePen>
      <StringItem>
        <Value>pen1</Value>
      </StringItem>
      <StringItem>
        <Value>pen1</Value>
      </StringItem>
      <StringItem>
        <Value>pen1</Value>
      </StringItem>
    </NamePen>
    <NameGraphics>
      <StringItem>
        <Value>kl210_166</Value>
      </StringItem>
    </NameGraphics>
    <ValueName>__STD_2</ValueName>
    <TypRoute>0</TypRoute>
    <ValueType>BitStruct</ValueType>
    <ValuePos>6</ValuePos>
  </Route>
  <Route>
    <Name>Key_BSSUS</Name>
    <NamePen>
      <StringItem>
        <Value>pen1</Value>
      </StringItem>
      <StringItem>
        <Value>pen1</Value>
      </StringItem>
      <StringItem>
        <Value>pen1</Value>
      </StringItem>
    </NamePen>
    <NameGraphics>
      <StringItem>
        <Value>kl218_36</Value>
      </StringItem>
    </NameGraphics>
    <ValueName>__STD_2</ValueName>
    <TypRoute>0</TypRoute>
    <ValueType>BitStruct</ValueType>
    <ValuePos>7</ValuePos>
  </Route>
  <Route>
    <Name>Key_BC1</Name>
    <NamePen>
      <StringItem>
        <Value>pen1</Value>
      </StringItem>
      <StringItem>
        <Value>pen1</Value>
      </StringItem>
      <StringItem>
        <Value>pen1</Value>
      </StringItem>
    </NamePen>
    <NameGraphics>
      <StringItem>
        <Value>kl201_23</Value>
      </StringItem>
    </NameGraphics>
    <ValueName>__STD_2</ValueName>
    <TypRoute>0</TypRoute>
    <ValueType>BitStruct</ValueType>
    <ValuePos>8</ValuePos>
  </Route>
  <Route>
    <Name>Key_BC2</Name>
    <NamePen>
      <StringItem>
        <Value>pen1</Value>
      </StringItem>
      <StringItem>
        <Value>pen1</Value>
      </StringItem>
      <StringItem>
        <Value>pen1</Value>
      </StringItem>
    </NamePen>
    <NameGraphics>
      <StringItem>
        <Value>kl202_198</Value>
      </StringItem>
    </NameGraphics>
    <ValueName>__STD_2</ValueName>
    <TypRoute>0</TypRoute>
    <ValueType>BitStruct</ValueType>
    <ValuePos>9</ValuePos>
  </Route>
  <Route>
    <Name>CH54_no</Name>
    <NamePen>
      <StringItem>
        <Value>pBlack</Value>
      </StringItem>
      <StringItem>
        <Value>pBlue</Value>
      </StringItem>
    </NamePen>
    <NameGraphics>
      <StringItem>
        <Value>vl285_193</Value>
      </StringItem>
      <StringItem>
        <Value>kl129_74</Value>
      </StringItem>
      <StringItem>
        <Value>l80_29</Value>
      </StringItem>
      <StringItem>
        <Value>l81_72</Value>
      </StringItem>
      <StringItem>
        <Value>kl176_174</Value>
      </StringItem>
    </NameGraphics>
    <ValueName>__STD_1</ValueName>
    <TypRoute>0</TypRoute>
    <ValueType>BitStruct</ValueType>
    <ValuePos>27</ValuePos>
  </Route>
  <Route>
    <Name>key_9</Name>
    <NamePen>
      <StringItem>
        <Value>pen1</Value>
      </StringItem>
      <StringItem>
        <Value>pen1</Value>
      </StringItem>
    </NamePen>
    <NameGraphics>
      <StringItem>
        <Value>kl219_80</Value>
      </StringItem>
    </NameGraphics>
    <ValueName>__STD_1</ValueName>
    <TypRoute>0</TypRoute>
    <ValueType>BitStruct</ValueType>
    <ValuePos>28</ValuePos>
  </Route>
  <Route>
    <Name>TransBS</Name>
    <NamePen>
      <StringItem>
        <Value>pen1</Value>
      </StringItem>
      <StringItem>
        <Value>pen1</Value>
      </StringItem>
    </NamePen>
    <NameGraphics>
      <StringItem>
        <Value>kl261_171</Value>
      </StringItem>
    </NameGraphics>
    <ValueName>__STD_1</ValueName>
    <TypRoute>0</TypRoute>
    <ValueType>BitStruct</ValueType>
    <ValuePos>29</ValuePos>
  </Route>
  <Route>
    <Name>BSvSUS</Name>
    <NamePen>
      <StringItem>
        <Value>pen1</Value>
      </StringItem>
      <StringItem>
        <Value>pen1</Value>
      </StringItem>
    </NamePen>
    <NameGraphics>
      <StringItem>
        <Value>kl259_121</Value>
      </StringItem>
    </NameGraphics>
    <ValueName>__STD_1</ValueName>
    <TypRoute>0</TypRoute>
    <ValueType>BitStruct</ValueType>
    <ValuePos>30</ValuePos>
  </Route>
  <Route>
    <Name>Bw31</Name>
    <NamePen>
      <StringItem>
        <Value>pBlack</Value>
      </StringItem>
      <StringItem>
        <Value>pBlue</Value>
      </StringItem>
    </NamePen>
    <NameGraphics>
      <StringItem>
        <Value>l24_3</Value>
      </StringItem>
      <StringItem>
        <Value>kl245_132</Value>
      </StringItem>
    </NameGraphics>
    <ValueName>__MNEMO_RES_52</ValueName>
    <TypRoute>0</TypRoute>
    <ValueType>BitStruct</ValueType>
    <ValuePos>0</ValuePos>
  </Route>
  <Route>
    <Name>Bw33</Name>
    <NamePen>
      <StringItem>
        <Value>pBlack</Value>
      </StringItem>
      <StringItem>
        <Value>pBlue</Value>
      </StringItem>
    </NamePen>
    <NameGraphics>
      <StringItem>
        <Value>l27_14</Value>
      </StringItem>
      <StringItem>
        <Value>l28_1</Value>
      </StringItem>
    </NameGraphics>
    <ValueName>__MNEMO_RES_52</ValueName>
    <TypRoute>0</TypRoute>
    <ValueType>BitStruct</ValueType>
    <ValuePos>1</ValuePos>
  </Route>
  <Route>
    <Name>Bw32</Name>
    <NamePen>
      <StringItem>
        <Value>pBlack</Value>
      </StringItem>
      <StringItem>
        <Value>pen1</Value>
      </StringItem>
    </NamePen>
    <NameGraphics>
      <StringItem>
        <Value>kl247_120</Value>
      </StringItem>
    </NameGraphics>
    <ValueName>__MNEMO_RES_52</ValueName>
    <TypRoute>0</TypRoute>
    <ValueType>BitStruct</ValueType>
    <ValuePos>2</ValuePos>
  </Route>
  <Route>
    <Name>Bl48</Name>
    <NamePen>
      <StringItem>
        <Value>pBlack</Value>
      </StringItem>
      <StringItem>
        <Value>pBlue</Value>
      </StringItem>
    </NamePen>
    <NameGraphics>
      <StringItem>
        <Value>l29_28</Value>
      </StringItem>
      <StringItem>
        <Value>kl199_198</Value>
      </StringItem>
    </NameGraphics>
    <ValueName>__MNEMO_RES_52</ValueName>
    <TypRoute>0</TypRoute>
    <ValueType>BitStruct</ValueType>
    <ValuePos>3</ValuePos>
  </Route>
  <Route>
    <Name>bw34</Name>
    <NamePen>
      <StringItem>
        <Value>pen1</Value>
      </StringItem>
      <StringItem>
        <Value>pen1</Value>
      </StringItem>
    </NamePen>
    <NameGraphics>
      <StringItem>
        <Value>kl220_80</Value>
      </StringItem>
    </NameGraphics>
    <ValueName>__MNEMO_RES_52</ValueName>
    <TypRoute>0</TypRoute>
    <ValueType>BitStruct</ValueType>
    <ValuePos>4</ValuePos>
  </Route>
  <Route>
    <Name>bw38</Name>
    <NamePen>
      <StringItem>
        <Value>pBlack</Value>
      </StringItem>
      <StringItem>
        <Value>pBlue</Value>
      </StringItem>
    </NamePen>
    <NameGraphics>
      <StringItem>
        <Value>kl215_84</Value>
      </StringItem>
      <StringItem>
        <Value>l50_30</Value>
      </StringItem>
      <StringItem>
        <Value>kl173_121</Value>
      </StringItem>
    </NameGraphics>
    <ValueName>__MNEMO_RES_52</ValueName>
    <TypRoute>0</TypRoute>
    <ValueType>BitStruct</ValueType>
    <ValuePos>5</ValuePos>
  </Route>
  <Route>
    <Name>Bl49</Name>
    <NamePen>
      <StringItem>
        <Value>pBlack</Value>
      </StringItem>
      <StringItem>
        <Value>pBlue</Value>
      </StringItem>
    </NamePen>
    <NameGraphics>
      <StringItem>
        <Value>l49_39</Value>
      </StringItem>
      <StringItem>
        <Value>kl172_56</Value>
      </StringItem>
    </NameGraphics>
    <ValueName>__MNEMO_RES_52</ValueName>
    <TypRoute>0</TypRoute>
    <ValueType>BitStruct</ValueType>
    <ValuePos>6</ValuePos>
  </Route>
  <Route>
    <Name>Bw30</Name>
    <NamePen>
      <StringItem>
        <Value>pen1</Value>
      </StringItem>
      <StringItem>
        <Value>pen1</Value>
      </StringItem>
    </NamePen>
    <NameGraphics>
      <StringItem>
        <Value>kl217_152</Value>
      </StringItem>
    </NameGraphics>
    <ValueName>__MNEMO_RES_52</ValueName>
    <TypRoute>0</TypRoute>
    <ValueType>BitStruct</ValueType>
    <ValuePos>7</ValuePos>
  </Route>
  <Route>
    <Name>Bsh80</Name>
    <NamePen>
      <StringItem>
        <Value>pBlack</Value>
      </StringItem>
      <StringItem>
        <Value>pBlue</Value>
      </StringItem>
    </NamePen>
    <NameGraphics>
      <StringItem>
        <Value>vl335_93</Value>
      </StringItem>
      <StringItem>
        <Value>kl102_76</Value>
      </StringItem>
      <StringItem>
        <Value>l84_64</Value>
      </StringItem>
      <StringItem>
        <Value>l86_40</Value>
      </StringItem>
      <StringItem>
        <Value>l88_33</Value>
      </StringItem>
      <StringItem>
        <Value>kl163_63</Value>
      </StringItem>
    </NameGraphics>
    <ValueName>__MNEMO_RES_52</ValueName>
    <TypRoute>0</TypRoute>
    <ValueType>BitStruct</ValueType>
    <ValuePos>8</ValuePos>
  </Route>
  <Route>
    <Name>Bsh81</Name>
    <NamePen>
      <StringItem>
        <Value>pBlack</Value>
      </StringItem>
      <StringItem>
        <Value>pBlue</Value>
      </StringItem>
    </NamePen>
    <NameGraphics>
      <StringItem>
        <Value>vl337_20</Value>
      </StringItem>
      <StringItem>
        <Value>kl105_25</Value>
      </StringItem>
      <StringItem>
        <Value>l89_9</Value>
      </StringItem>
      <StringItem>
        <Value>l92_44</Value>
      </StringItem>
      <StringItem>
        <Value>l93_57</Value>
      </StringItem>
      <StringItem>
        <Value>l95_75</Value>
      </StringItem>
      <StringItem>
        <Value>kl180_43</Value>
      </StringItem>
    </NameGraphics>
    <ValueName>__MNEMO_RES_52</ValueName>
    <TypRoute>0</TypRoute>
    <ValueType>BitStruct</ValueType>
    <ValuePos>9</ValuePos>
  </Route>
  <Route>
    <Name>Bw35sin</Name>
    <NamePen>
      <StringItem>
        <Value>pBlack</Value>
      </StringItem>
      <StringItem>
        <Value>pBlue</Value>
      </StringItem>
    </NamePen>
    <NameGraphics>
      <StringItem>
        <Value>l82_63</Value>
      </StringItem>
      <StringItem>
        <Value>kl160_77</Value>
      </StringItem>
    </NameGraphics>
    <ValueName>__MNEMO_RES_52</ValueName>
    <TypRoute>0</TypRoute>
    <ValueType>BitStruct</ValueType>
    <ValuePos>10</ValuePos>
  </Route>
  <Route>
    <Name>Bw35red</Name>
    <NamePen>
      <StringItem>
        <Value>pBlack</Value>
      </StringItem>
      <StringItem>
        <Value>pRed</Value>
      </StringItem>
    </NamePen>
    <NameGraphics>
      <StringItem>
        <Value>l83_82</Value>
      </StringItem>
      <StringItem>
        <Value>kl159_0</Value>
      </StringItem>
    </NameGraphics>
    <ValueName>__MNEMO_RES_52</ValueName>
    <TypRoute>0</TypRoute>
    <ValueType>BitStruct</ValueType>
    <ValuePos>10</ValuePos>
  </Route>
  <Route>
    <Name>bl_44</Name>
    <NamePen>
      <StringItem>
        <Value>pBlack</Value>
      </StringItem>
      <StringItem>
        <Value>pBlue</Value>
      </StringItem>
    </NamePen>
    <NameGraphics>
      <StringItem>
        <Value>kl114_5</Value>
      </StringItem>
      <StringItem>
        <Value>l23_8</Value>
      </StringItem>
      <StringItem>
        <Value>l22_12</Value>
      </StringItem>
      <StringItem>
        <Value>kl169_60</Value>
      </StringItem>
    </NameGraphics>
    <ValueName>__MNEMO_RES_52</ValueName>
    <TypRoute>0</TypRoute>
    <ValueType>BitStruct</ValueType>
    <ValuePos>11</ValuePos>
  </Route>
  <Route>
    <Name>bl46</Name>
    <NamePen>
      <StringItem>
        <Value>pBlack</Value>
      </StringItem>
      <StringItem>
        <Value>pBlue</Value>
      </StringItem>
    </NamePen>
    <NameGraphics>
      <StringItem>
        <Value>kl115_13</Value>
      </StringItem>
      <StringItem>
        <Value>l40_35</Value>
      </StringItem>
      <StringItem>
        <Value>l41_13</Value>
      </StringItem>
      <StringItem>
        <Value>kl170_2</Value>
      </StringItem>
    </NameGraphics>
    <ValueName>__MNEMO_RES_52</ValueName>
    <TypRoute>0</TypRoute>
    <ValueType>BitStruct</ValueType>
    <ValuePos>12</ValuePos>
  </Route>
  <Route>
    <Name>Bsh58</Name>
    <NamePen>
      <StringItem>
        <Value>pBlack</Value>
      </StringItem>
      <StringItem>
        <Value>pBlue</Value>
      </StringItem>
    </NamePen>
    <NameGraphics>
      <StringItem>
        <Value>vl339_142</Value>
      </StringItem>
      <StringItem>
        <Value>vl343_323</Value>
      </StringItem>
      <StringItem>
        <Value>kl114_5</Value>
      </StringItem>
    </NameGraphics>
    <ValueName>__MNEMO_RES_52</ValueName>
    <TypRoute>0</TypRoute>
    <ValueType>BitStruct</ValueType>
    <ValuePos>13</ValuePos>
  </Route>
  <Route>
    <Name>B_CC5</Name>
    <NamePen>
      <StringItem>
        <Value>pBlack</Value>
      </StringItem>
      <StringItem>
        <Value>pBlue</Value>
      </StringItem>
    </NamePen>
    <NameGraphics>
      <StringItem>
        <Value>vl338_290</Value>
      </StringItem>
      <StringItem>
        <Value>kl114_5</Value>
      </StringItem>
    </NameGraphics>
    <ValueName>__MNEMO_RES_52</ValueName>
    <TypRoute>0</TypRoute>
    <ValueType>BitStruct</ValueType>
    <ValuePos>14</ValuePos>
  </Route>
  <Route>
    <Name>Bkovk15</Name>
    <NamePen>
      <StringItem>
        <Value>pBlack</Value>
      </StringItem>
      <StringItem>
        <Value>pBlue</Value>
      </StringItem>
    </NamePen>
    <NameGraphics>
      <StringItem>
        <Value>vl342_48</Value>
      </StringItem>
      <StringItem>
        <Value>kl114_5</Value>
      </StringItem>
    </NameGraphics>
    <ValueName>__MNEMO_RES_52</ValueName>
    <TypRoute>0</TypRoute>
    <ValueType>BitStruct</ValueType>
    <ValuePos>15</ValuePos>
  </Route>
  <Route>
    <Name>Bsh57</Name>
    <NamePen>
      <StringItem>
        <Value>pBlack</Value>
      </StringItem>
      <StringItem>
        <Value>pBlue</Value>
      </StringItem>
    </NamePen>
    <NameGraphics>
      <StringItem>
        <Value>vl340_338</Value>
      </StringItem>
      <StringItem>
        <Value>vl341_286</Value>
      </StringItem>
      <StringItem>
        <Value>kl114_5</Value>
      </StringItem>
    </NameGraphics>
    <ValueName>__MNEMO_RES_52</ValueName>
    <TypRoute>0</TypRoute>
    <ValueType>BitStruct</ValueType>
    <ValuePos>16</ValuePos>
  </Route>
  <Route>
    <Name>B_CC2</Name>
    <NamePen>
      <StringItem>
        <Value>pBlack</Value>
      </StringItem>
      <StringItem>
        <Value>pBlue</Value>
      </StringItem>
    </NamePen>
    <NameGraphics>
      <StringItem>
        <Value>vl337_211</Value>
      </StringItem>
      <StringItem>
        <Value>vl324_307</Value>
      </StringItem>
      <StringItem>
        <Value>kl149_101</Value>
      </StringItem>
      <StringItem>
        <Value>l59_26</Value>
      </StringItem>
      <StringItem>
        <Value>kl166_76</Value>
      </StringItem>
      <StringItem>
        <Value>kl114_5</Value>
      </StringItem>
      <StringItem>
        <Value>kl203_176</Value>
      </StringItem>
    </NameGraphics>
    <ValueName>__MNEMO_RES_52</ValueName>
    <TypRoute>0</TypRoute>
    <ValueType>BitStruct</ValueType>
    <ValuePos>17</ValuePos>
  </Route>
  <Route>
    <Name>Bsh56</Name>
    <NamePen>
      <StringItem>
        <Value>pBlack</Value>
      </StringItem>
      <StringItem>
        <Value>pBlue</Value>
      </StringItem>
    </NamePen>
    <NameGraphics>
      <StringItem>
        <Value>vl344_342</Value>
      </StringItem>
      <StringItem>
        <Value>vl345_190</Value>
      </StringItem>
      <StringItem>
        <Value>kl150_116</Value>
      </StringItem>
      <StringItem>
        <Value>vl325_118</Value>
      </StringItem>
      <StringItem>
        <Value>l61_55</Value>
      </StringItem>
      <StringItem>
        <Value>l62_1</Value>
      </StringItem>
      <StringItem>
        <Value>kl139_67</Value>
      </StringItem>
      <StringItem>
        <Value>kl138_41</Value>
      </StringItem>
      <StringItem>
        <Value>kl137_55</Value>
      </StringItem>
      <StringItem>
        <Value>kl136_55</Value>
      </StringItem>
      <StringItem>
        <Value>kl167_142</Value>
      </StringItem>
      <StringItem>
        <Value>kl115_13</Value>
      </StringItem>
    </NameGraphics>
    <ValueName>__MNEMO_RES_52</ValueName>
    <TypRoute>0</TypRoute>
    <ValueType>BitStruct</ValueType>
    <ValuePos>18</ValuePos>
  </Route>
  <Route>
    <Name>Bkovk10</Name>
    <NamePen>
      <StringItem>
        <Value>pBlack</Value>
      </StringItem>
      <StringItem>
        <Value>pBlue</Value>
      </StringItem>
    </NamePen>
    <NameGraphics>
      <StringItem>
        <Value>vl346_198</Value>
      </StringItem>
      <StringItem>
        <Value>kl115_13</Value>
      </StringItem>
      <StringItem>
        <Value>vl317_105</Value>
      </StringItem>
      <StringItem>
        <Value>kl265_89</Value>
      </StringItem>
      <StringItem>
        <Value>l77_53</Value>
      </StringItem>
      <StringItem>
        <Value>kl177_15</Value>
      </StringItem>
    </NameGraphics>
    <ValueName>__MNEMO_RES_52</ValueName>
    <TypRoute>0</TypRoute>
    <ValueType>BitStruct</ValueType>
    <ValuePos>19</ValuePos>
  </Route>
  <Route>
    <Name>B_CC1</Name>
    <NamePen>
      <StringItem>
        <Value>pBlack</Value>
      </StringItem>
      <StringItem>
        <Value>pBlue</Value>
      </StringItem>
    </NamePen>
    <NameGraphics>
      <StringItem>
        <Value>vl347_264</Value>
      </StringItem>
      <StringItem>
        <Value>kl115_13</Value>
      </StringItem>
    </NameGraphics>
    <ValueName>__MNEMO_RES_52</ValueName>
    <TypRoute>0</TypRoute>
    <ValueType>BitStruct</ValueType>
    <ValuePos>20</ValuePos>
  </Route>
  <Route>
    <Name>Bwi29</Name>
    <NamePen>
      <StringItem>
        <Value>pBlack</Value>
      </StringItem>
      <StringItem>
        <Value>pBlue</Value>
      </StringItem>
    </NamePen>
    <NameGraphics>
      <StringItem>
        <Value>l57_53</Value>
      </StringItem>
      <StringItem>
        <Value>kl204_83</Value>
      </StringItem>
      <StringItem>
        <Value>l63_58</Value>
      </StringItem>
      <StringItem>
        <Value>kl144_2</Value>
      </StringItem>
      <StringItem>
        <Value>kl143_19</Value>
      </StringItem>
    </NameGraphics>
    <ValueName>__MNEMO_RES_52</ValueName>
    <TypRoute>0</TypRoute>
    <ValueType>BitStruct</ValueType>
    <ValuePos>21</ValuePos>
  </Route>
  <Route>
    <Name>Bwi27</Name>
    <NamePen>
      <StringItem>
        <Value>pBlack</Value>
      </StringItem>
      <StringItem>
        <Value>pBlue</Value>
      </StringItem>
    </NamePen>
    <NameGraphics>
      <StringItem>
        <Value>kl147_101</Value>
      </StringItem>
      <StringItem>
        <Value>kl145_135</Value>
      </StringItem>
      <StringItem>
        <Value>l57_53</Value>
      </StringItem>
      <StringItem>
        <Value>l55_48</Value>
      </StringItem>
      <StringItem>
        <Value>l312_308</Value>
      </StringItem>
      <StringItem>
        <Value>l53_19</Value>
      </StringItem>
      <StringItem>
        <Value>l69_55</Value>
      </StringItem>
      <StringItem>
        <Value>l54_12</Value>
      </StringItem>
      <StringItem>
        <Value>kl191_35</Value>
      </StringItem>
      <StringItem>
        <Value>l56_4</Value>
      </StringItem>
      <StringItem>
        <Value>l64_19</Value>
      </StringItem>
      <StringItem>
        <Value>kl164_77</Value>
      </StringItem>
    </NameGraphics>
    <ValueName>__MNEMO_RES_52</ValueName>
    <TypRoute>0</TypRoute>
    <ValueType>BitStruct</ValueType>
    <ValuePos>22</ValuePos>
  </Route>
  <Route>
    <Name>B_pitSAS</Name>
    <NamePen>
      <StringItem>
        <Value>pBlack</Value>
      </StringItem>
      <StringItem>
        <Value>pBlue</Value>
      </StringItem>
    </NamePen>
    <NameGraphics>
      <StringItem>
        <Value>kl148_34</Value>
      </StringItem>
      <StringItem>
        <Value>kl146_86</Value>
      </StringItem>
    </NameGraphics>
    <ValueName>__MNEMO_RES_52</ValueName>
    <TypRoute>0</TypRoute>
    <ValueType>BitStruct</ValueType>
    <ValuePos>23</ValuePos>
  </Route>
  <Route>
    <Name>Bwi26</Name>
    <NamePen>
      <StringItem>
        <Value>pBlack</Value>
      </StringItem>
      <StringItem>
        <Value>pBlue</Value>
      </StringItem>
    </NamePen>
    <NameGraphics>
      <StringItem>
        <Value>kl148_34</Value>
      </StringItem>
      <StringItem>
        <Value>kl146_86</Value>
      </StringItem>
      <StringItem>
        <Value>l58_17</Value>
      </StringItem>
      <StringItem>
        <Value>l312_308</Value>
      </StringItem>
      <StringItem>
        <Value>l53_19</Value>
      </StringItem>
      <StringItem>
        <Value>l69_55</Value>
      </StringItem>
      <StringItem>
        <Value>l54_12</Value>
      </StringItem>
      <StringItem>
        <Value>kl191_35</Value>
      </StringItem>
      <StringItem>
        <Value>l56_4</Value>
      </StringItem>
      <StringItem>
        <Value>l64_19</Value>
      </StringItem>
      <StringItem>
        <Value>kl164_77</Value>
      </StringItem>
      <StringItem>
        <Value>l63_58</Value>
      </StringItem>
      <StringItem>
        <Value>kl144_2</Value>
      </StringItem>
      <StringItem>
        <Value>kl143_19</Value>
      </StringItem>
      <StringItem>
        <Value>l58_17</Value>
      </StringItem>
      <StringItem>
        <Value>kl148_34</Value>
      </StringItem>
      <StringItem>
        <Value>kl146_86</Value>
      </StringItem>
      <StringItem>
        <Value>kl203_176</Value>
      </StringItem>
    </NameGraphics>
    <ValueName>__MNEMO_RES_52</ValueName>
    <TypRoute>0</TypRoute>
    <ValueType>BitStruct</ValueType>
    <ValuePos>24</ValuePos>
  </Route>
  <Route>
    <Name>Bwi27</Name>
    <NamePen>
      <StringItem>
        <Value>pBlack</Value>
      </StringItem>
      <StringItem>
        <Value>pBlue</Value>
      </StringItem>
    </NamePen>
    <NameGraphics>
      <StringItem>
        <Value>l54_46</Value>
      </StringItem>
      <StringItem>
        <Value>kl135_31</Value>
      </StringItem>
      <StringItem>
        <Value>kl134_29</Value>
      </StringItem>
      <StringItem>
        <Value>kl133_37</Value>
      </StringItem>
      <StringItem>
        <Value>kl132_68</Value>
      </StringItem>
      <StringItem>
        <Value>l55_48</Value>
      </StringItem>
      <StringItem>
        <Value>l312_308</Value>
      </StringItem>
      <StringItem>
        <Value>l53_19</Value>
      </StringItem>
      <StringItem>
        <Value>l69_55</Value>
      </StringItem>
      <StringItem>
        <Value>l54_12</Value>
      </StringItem>
      <StringItem>
        <Value>kl191_35</Value>
      </StringItem>
      <StringItem>
        <Value>l56_4</Value>
      </StringItem>
      <StringItem>
        <Value>l64_19</Value>
      </StringItem>
      <StringItem>
        <Value>kl164_77</Value>
      </StringItem>
    </NameGraphics>
    <ValueName>__MNEMO_RES_52</ValueName>
    <TypRoute>0</TypRoute>
    <ValueType>BitStruct</ValueType>
    <ValuePos>25</ValuePos>
  </Route>
  <Route>
    <Name>BkSP6</Name>
    <NamePen>
      <StringItem>
        <Value>pBlack</Value>
      </StringItem>
      <StringItem>
        <Value>pBlue</Value>
      </StringItem>
    </NamePen>
    <NameGraphics>
      <StringItem>
        <Value>vl327_173</Value>
      </StringItem>
      <StringItem>
        <Value>kl152_104</Value>
      </StringItem>
      <StringItem>
        <Value>l70_13</Value>
      </StringItem>
      <StringItem>
        <Value>l72_23</Value>
      </StringItem>
      <StringItem>
        <Value>kl168_108</Value>
      </StringItem>
    </NameGraphics>
    <ValueName>__MNEMO_RES_52</ValueName>
    <TypRoute>0</TypRoute>
    <ValueType>BitStruct</ValueType>
    <ValuePos>26</ValuePos>
  </Route>
  <Route>
    <Name>BkSP2</Name>
    <NamePen>
      <StringItem>
        <Value>pBlack</Value>
      </StringItem>
      <StringItem>
        <Value>pBlue</Value>
      </StringItem>
    </NamePen>
    <NameGraphics>
      <StringItem>
        <Value>vl328_170</Value>
      </StringItem>
      <StringItem>
        <Value>kl153_112</Value>
      </StringItem>
      <StringItem>
        <Value>l71_35</Value>
      </StringItem>
      <StringItem>
        <Value>l72_23</Value>
      </StringItem>
      <StringItem>
        <Value>kl168_108</Value>
      </StringItem>
    </NameGraphics>
    <ValueName>__MNEMO_RES_52</ValueName>
    <TypRoute>0</TypRoute>
    <ValueType>BitStruct</ValueType>
    <ValuePos>27</ValuePos>
  </Route>
  <Route>
    <Name>Bwi25</Name>
    <NamePen>
      <StringItem>
        <Value>pBlack</Value>
      </StringItem>
      <StringItem>
        <Value>pBlue</Value>
      </StringItem>
    </NamePen>
    <NameGraphics>
      <StringItem>
        <Value>l65_29</Value>
      </StringItem>
      <StringItem>
        <Value>kl202_87</Value>
      </StringItem>
      <StringItem>
        <Value>l66_37</Value>
      </StringItem>
      <StringItem>
        <Value>l64_19</Value>
      </StringItem>
      <StringItem>
        <Value>kl164_77</Value>
      </StringItem>
      <StringItem>
        <Value>l67_12</Value>
      </StringItem>
      <StringItem>
        <Value>l68_28</Value>
      </StringItem>
      <StringItem>
        <Value>l54_12</Value>
      </StringItem>
      <StringItem>
        <Value>kl191_35</Value>
      </StringItem>
    </NameGraphics>
    <ValueName>__MNEMO_RES_52</ValueName>
    <TypRoute>0</TypRoute>
    <ValueType>BitStruct</ValueType>
    <ValuePos>28</ValuePos>
  </Route>
  <Route>
    <Name>Bsh55</Name>
    <NamePen>
      <StringItem>
        <Value>pBlack</Value>
      </StringItem>
      <StringItem>
        <Value>pBlue</Value>
      </StringItem>
    </NamePen>
    <NameGraphics>
      <StringItem>
        <Value>vl326_80</Value>
      </StringItem>
      <StringItem>
        <Value>kl151_86</Value>
      </StringItem>
      <StringItem>
        <Value>l60_2</Value>
      </StringItem>
      <StringItem>
        <Value>l62_1</Value>
      </StringItem>
      <StringItem>
        <Value>kl139_67</Value>
      </StringItem>
      <StringItem>
        <Value>kl138_41</Value>
      </StringItem>
      <StringItem>
        <Value>kl137_55</Value>
      </StringItem>
      <StringItem>
        <Value>kl136_55</Value>
      </StringItem>
      <StringItem>
        <Value>kl167_142</Value>
      </StringItem>
    </NameGraphics>
    <ValueName>__MNEMO_RES_52</ValueName>
    <TypRoute>0</TypRoute>
    <ValueType>BitStruct</ValueType>
    <ValuePos>29</ValuePos>
  </Route>
  <Route>
    <Name>B1244</Name>
    <NamePen>
      <StringItem>
        <Value>pen1</Value>
      </StringItem>
      <StringItem>
        <Value>pen1</Value>
      </StringItem>
    </NamePen>
    <NameGraphics>
      <StringItem>
        <Value>kl263_228</Value>
      </StringItem>
    </NameGraphics>
    <ValueName>__STD_2</ValueName>
    <TypRoute>0</TypRoute>
    <ValueType>BitStruct</ValueType>
    <ValuePos>12</ValuePos>
  </Route>
  <Route>
    <Name>Bwi28</Name>
    <NamePen>
      <StringItem>
        <Value>pBlack</Value>
      </StringItem>
      <StringItem>
        <Value>pBlue</Value>
      </StringItem>
    </NamePen>
    <NameGraphics>
      <StringItem>
        <Value>l54_46</Value>
      </StringItem>
      <StringItem>
        <Value>kl263_228</Value>
      </StringItem>
      <StringItem>
        <Value>l54_46</Value>
      </StringItem>
      <StringItem>
        <Value>l55_48</Value>
      </StringItem>
      <StringItem>
        <Value>l312_308</Value>
      </StringItem>
      <StringItem>
        <Value>l56_4</Value>
      </StringItem>
      <StringItem>
        <Value>l64_19</Value>
      </StringItem>
      <StringItem>
        <Value>kl164_77</Value>
      </StringItem>
      <StringItem>
        <Value>l53_19</Value>
      </StringItem>
      <StringItem>
        <Value>l69_55</Value>
      </StringItem>
      <StringItem>
        <Value>l54_12</Value>
      </StringItem>
      <StringItem>
        <Value>kl191_35</Value>
      </StringItem>
      <StringItem>
        <Value>kl201_23</Value>
      </StringItem>
    </NameGraphics>
    <ValueName>__MNEMO_RES_52</ValueName>
    <TypRoute>0</TypRoute>
    <ValueType>BitStruct</ValueType>
    <ValuePos>31</ValuePos>
  </Route>
  <Route>
    <Name>SP_</Name>
    <NamePen>
      <StringItem>
        <Value>pBlackPunktir</Value>
      </StringItem>
      <StringItem>
        <Value>pBlackPunktir</Value>
      </StringItem>
    </NamePen>
    <NameGraphics>
      <StringItem>
        <Value>l380_165</Value>
      </StringItem>
      <StringItem>
        <Value>l381_347</Value>
      </StringItem>
    </NameGraphics>
    <ValueName>__SEP_3</ValueName>
    <TypRoute>0</TypRoute>
    <ValueType>BitStruct</ValueType>
    <ValuePos>0</ValuePos>
  </Route>
  <Route>
    <Name>lineTRPODKL</Name>
    <NamePen>
      <StringItem>
        <Value>pBlack</Value>
      </StringItem>
      <StringItem>
        <Value>pBlue</Value>
      </StringItem>
    </NamePen>
    <NameGraphics />
    <ValueName>__STD_2</ValueName>
    <TypRoute>0</TypRoute>
    <ValueType>BitStruct</ValueType>
    <ValuePos>4</ValuePos>
  </Route>
  <Route>
    <Name>p66</Name>
    <NamePen>
      <StringItem>
        <Value>pBlack</Value>
      </StringItem>
      <StringItem>
        <Value>pRed</Value>
      </StringItem>
    </NamePen>
    <NameGraphics>
      <StringItem>
        <Value>vl322_307</Value>
      </StringItem>
      <StringItem>
        <Value>vl318_192</Value>
      </StringItem>
      <StringItem>
        <Value>vl311_96</Value>
      </StringItem>
      <StringItem>
        <Value>vl360_314</Value>
      </StringItem>
      <StringItem>
        <Value>vl359_328</Value>
      </StringItem>
    </NameGraphics>
    <ValueName>__URO_6</ValueName>
    <TypRoute>0</TypRoute>
    <ValueType>BitStruct</ValueType>
    <ValuePos>23</ValuePos>
  </Route>
  <Route>
    <Name>p65</Name>
    <NamePen>
      <StringItem>
        <Value>pBlack</Value>
      </StringItem>
      <StringItem>
        <Value>pRed</Value>
      </StringItem>
    </NamePen>
    <NameGraphics>
      <StringItem>
        <Value>vl323_195</Value>
      </StringItem>
      <StringItem>
        <Value>vl361_116</Value>
      </StringItem>
    </NameGraphics>
    <ValueName>__URO_6</ValueName>
    <TypRoute>0</TypRoute>
    <ValueType>BitStruct</ValueType>
    <ValuePos>24</ValuePos>
  </Route>
  <Route>
    <Name>m5</Name>
    <NamePen>
      <StringItem>
        <Value>pBlack</Value>
      </StringItem>
      <StringItem>
        <Value>pBlue</Value>
      </StringItem>
    </NamePen>
    <NameGraphics>
      <StringItem>
        <Value>vl306_228</Value>
      </StringItem>
    </NameGraphics>
    <ValueName>__URO_6</ValueName>
    <TypRoute>0</TypRoute>
    <ValueType>BitStruct</ValueType>
    <ValuePos>20</ValuePos>
  </Route>
  <Route>
    <Name>p1.1</Name>
    <NamePen>
      <StringItem>
        <Value>pBlack</Value>
      </StringItem>
      <StringItem>
        <Value>pRed</Value>
      </StringItem>
    </NamePen>
    <NameGraphics>
      <StringItem>
        <Value>vl321_230</Value>
      </StringItem>
    </NameGraphics>
    <ValueName>__MNEMO_RES_5</ValueName>
    <TypRoute>0</TypRoute>
    <ValueType>BitStruct</ValueType>
    <ValuePos>14</ValuePos>
  </Route>
  <Route>
    <Name>p21.4</Name>
    <NamePen>
      <StringItem>
        <Value>pBlack</Value>
      </StringItem>
      <StringItem>
        <Value>pRed</Value>
      </StringItem>
    </NamePen>
    <NameGraphics>
      <StringItem>
        <Value>vl364_31</Value>
      </StringItem>
    </NameGraphics>
    <ValueName>__MNEMO_RES_5</ValueName>
    <TypRoute>0</TypRoute>
    <ValueType>BitStruct</ValueType>
    <ValuePos>13</ValuePos>
  </Route>
  <Route>
    <Name>m83</Name>
    <NamePen>
      <StringItem>
        <Value>pBlack</Value>
      </StringItem>
      <StringItem>
        <Value>pBlue</Value>
      </StringItem>
    </NamePen>
    <NameGraphics>
      <StringItem>
        <Value>vl320_99</Value>
      </StringItem>
      <StringItem>
        <Value>vl319_119</Value>
      </StringItem>
    </NameGraphics>
    <ValueName>__MNEMO_RES_5</ValueName>
    <TypRoute>0</TypRoute>
    <ValueType>BitStruct</ValueType>
    <ValuePos>15</ValuePos>
  </Route>
  <Route>
    <Name>m85</Name>
    <NamePen>
      <StringItem>
        <Value>pBlack</Value>
      </StringItem>
      <StringItem>
        <Value>pBlue</Value>
      </StringItem>
    </NamePen>
    <NameGraphics>
      <StringItem>
        <Value>vl378_281</Value>
      </StringItem>
    </NameGraphics>
    <ValueName>__MNEMO_RES_5</ValueName>
    <TypRoute>0</TypRoute>
    <ValueType>BitStruct</ValueType>
    <ValuePos>16</ValuePos>
  </Route>
</ArrayOfRoute>